a_la_mode/__init__.py
a_la_mode/task.py
a_la_mode-0.1.2.dist-info/WHEEL
a_la_mode-0.1.2.dist-info/METADATA
a_la_mode-0.1.2.dist-info/RECORD
